doc/conf.py
prospect/__init__.py
prospect/analysis.py
prospect/communication.py
prospect/input.py
prospect/io.py
prospect/mcmc.py
prospect/optimiser.py
prospect/profile.py
prospect/run.py
prospect/kernels/__init__.py
prospect/kernels/analytical_kernel.py
prospect/kernels/base_kernel.py
prospect/kernels/cobaya_kernel.py
prospect/kernels/initialisation.py
prospect/kernels/montepython_kernel.py
prospect/tasks/__init__.py
prospect/tasks/analyse_global_optimisation_task.py
prospect/tasks/analyse_profile_task.py
prospect/tasks/base_analyse_task.py
prospect/tasks/base_task.py
prospect/tasks/initialise.py
prospect/tasks/initialise_optimiser_task.py
prospect/tasks/initialise_profile_task.py
prospect/tasks/mcmc_task.py
prospect/tasks/optimise_task.py
prospect_public-24.0.2.dist-info/METADATA
prospect_public-24.0.2.dist-info/WHEEL
prospect_public-24.0.2.dist-info/entry_points.txt
prospect_public-24.0.2.dist-info/top_level.txt
prospect_public-24.0.2.dist-info/RECORD
