Metadata-Version: 2.1
Name: prospect-public
Version: 24.0.2
Summary: A profile likelihood code for frequentist cosmological parameter inference
Author-email: Emil Brinch Holm <ebholm@phys.au.dk>, Thomas Tram <thomas.tram@phys.au.dk>
Project-URL: Homepage, https://github.com/AarhusCosmology/prospect_public
Project-URL: Bug Tracker, https://github.com/AarhusCosmology/prospect_public/issues
Classifier: Programming Language :: Python :: 3
Classifier: License :: OSI Approved :: GNU General Public License v3 (GPLv3)
Classifier: Operating System :: OS Independent
Requires-Python: >3.10.0
